{"site":{"title":"","description":null,"enableMobile":true,"websiteUrl":null,"faviconPath":null,"thumbnailSocialPath":null,"descriptionSocial":null,"titleSocial":null,"lang":"","width":1200,"headUser":"","headStyle":"","headScript":"","hostingProvider":"unifile","twitterSocial":null,"dataSources":{},"fonts":[{"family":"'Roboto', sans-serif","href":"https://fonts.googleapis.com/css?family=Roboto"}],"styles":{"all-style":{"className":"all-style","templateName":"text","displayName":"All style","styles":{"desktop":{"normal":{"className":"all-style","pseudoClass":"normal","All":{"font-family":"'Roboto', sans-serif"}}}}}},"isTemplate":false,"file":{"name":"index.html","folder":"e/main","path":"e/main/index.html","service":"github","url":"https://editor.silex.me/ce/github/get/e/main/index.html","absPath":"/ce/github/get/e/main/index.html"},"prodotypeDependencies":{},"data":{}},"pages":[{"id":"page-page-1","displayName":"Page 1","link":{"linkType":"LinkTypePage","href":"#!page-page-1"},"canDelete":true,"canProperties":true,"canMove":true,"canRename":true,"opened":false}],"elements":[{"id":"body-initial","pageNames":[],"classList":[],"type":"container-element","isSectionContent":false,"title":"","alt":null,"children":["silex-id-1478366444112-1","silex-id-1474394621033-3","silex-id-1478366450713-3"],"link":null,"enableEdit":false,"enableDrag":false,"enableDrop":true,"enableResize":{"top":false,"bottom":false,"left":false,"right":false},"selected":false,"useMinHeight":true,"visibility":{"desktop":true,"mobile":true},"style":{"desktop":{"background-color":"rgba(255,255,255,1)","position":"static"},"mobile":{}},"data":{"component":null},"innerHtml":"","tagName":"BODY"},{"id":"silex-id-1478366444112-1","pageNames":[],"classList":[],"type":"section-element","isSectionContent":false,"title":"","alt":null,"children":["silex-id-1478366444112-0"],"link":null,"enableEdit":false,"enableDrag":true,"enableDrop":true,"enableResize":{"top":false,"bottom":false,"left":false,"right":false},"selected":false,"useMinHeight":true,"visibility":{"desktop":true,"mobile":true},"style":{"desktop":{"background-color":"transparent","position":"static","margin-top":"-1px"},"mobile":{}},"data":{"component":null},"innerHtml":"","tagName":"SECTION"},{"id":"silex-id-1478366444112-0","pageNames":[],"classList":["website-width"],"type":"container-element","isSectionContent":true,"title":"","alt":null,"children":[],"link":null,"enableEdit":false,"enableDrag":false,"enableDrop":true,"enableResize":{"top":true,"bottom":true,"left":true,"right":true},"selected":false,"useMinHeight":true,"visibility":{"desktop":true,"mobile":true},"style":{"desktop":{"background-color":"transparent","height":"100px","position":"relative","margin-left":"auto","margin-right":"auto"},"mobile":{}},"data":{"component":null},"innerHtml":"","tagName":"DIV"},{"id":"silex-id-1474394621033-3","pageNames":[],"classList":[],"type":"section-element","isSectionContent":false,"title":"","alt":null,"children":["silex-id-1474394621032-2"],"link":null,"enableEdit":false,"enableDrag":true,"enableDrop":true,"enableResize":{"top":false,"bottom":false,"left":false,"right":false},"selected":false,"useMinHeight":true,"visibility":{"desktop":true,"mobile":true},"style":{"desktop":{"position":"static","margin-top":"-1px"},"mobile":{}},"data":{"component":null},"innerHtml":"","tagName":"SECTION"},{"id":"silex-id-1474394621032-2","pageNames":[],"classList":["website-width"],"type":"container-element","isSectionContent":true,"title":"","alt":null,"children":["silex-id-1633817675592-3","silex-id-1633817725897-4","silex-id-1633817803466-5","silex-id-1633816001125-1","silex-id-1633815765970-0"],"link":null,"enableEdit":false,"enableDrag":false,"enableDrop":true,"enableResize":{"top":true,"bottom":true,"left":true,"right":true},"selected":false,"useMinHeight":true,"visibility":{"desktop":true,"mobile":true},"style":{"desktop":{"background-color":"transparent","height":"600px","position":"relative","margin-left":"auto","margin-right":"auto"},"mobile":{}},"data":{"component":null},"innerHtml":"","tagName":"DIV"},{"id":"silex-id-1478366450713-3","pageNames":[],"classList":[],"type":"section-element","isSectionContent":false,"title":"","alt":null,"children":["silex-id-1478366450713-2"],"link":null,"enableEdit":false,"enableDrag":true,"enableDrop":true,"enableResize":{"top":false,"bottom":false,"left":false,"right":false},"selected":false,"useMinHeight":true,"visibility":{"desktop":true,"mobile":true},"style":{"desktop":{"background-color":"transparent","position":"static","margin-top":"-1px"},"mobile":{}},"data":{"component":null},"innerHtml":"","tagName":"SECTION"},{"id":"silex-id-1478366450713-2","pageNames":[],"classList":["website-width"],"type":"container-element","isSectionContent":true,"title":"","alt":null,"children":[],"link":null,"enableEdit":false,"enableDrag":false,"enableDrop":true,"enableResize":{"top":true,"bottom":true,"left":true,"right":true},"selected":false,"useMinHeight":true,"visibility":{"desktop":true,"mobile":true},"style":{"desktop":{"background-color":"transparent","height":"100px","position":"relative","margin-left":"auto","margin-right":"auto"},"mobile":{}},"data":{"component":null},"innerHtml":"","tagName":"DIV"},{"id":"silex-id-1633815765970-0","tagName":"DIV","type":"html-element","alt":null,"title":null,"isSectionContent":false,"visibility":{"desktop":true,"mobile":true},"style":{"mobile":{},"desktop":{"width":"308px","height":"113px","background-color":"rgb(255, 255, 255)","position":"absolute","top":"422px","left":"94.83341979980469px"}},"data":{"component":null},"children":[],"pageNames":["page-page-1"],"classList":[],"attr":{},"link":null,"enableEdit":true,"enableDrag":true,"enableDrop":false,"enableResize":{"top":true,"bottom":true,"left":true,"right":true},"selected":false,"useMinHeight":true,"innerHtml":"<style type=\"text/css\"> .btcpay-form { display: inline-flex; align-items: center; justify-content: center; } .btcpay-form--inline { flex-direction: row; } .btcpay-form--block { flex-direction: column; } .btcpay-form--inline .submit { margin-left: 15px; } .btcpay-form--block select { margin-bottom: 10px; } .btcpay-form .btcpay-custom-container{ text-align: center; }.btcpay-custom { display: flex; align-items: center; justify-content: center; } .btcpay-form .plus-minus { cursor:pointer; font-size:25px; line-height: 25px; background: #DFE0E1; height: 30px; width: 45px; border:none; border-radius: 60px; margin: auto 5px; display: inline-flex; justify-content: center; } .btcpay-form select { -moz-appearance: none; -webkit-appearance: none; appearance: none; color: currentColor; background: transparent; border:1px solid transparent; display: block; padding: 1px; margin-left: auto; margin-right: auto; font-size: 11px; cursor: pointer; } .btcpay-form select:hover { border-color: #ccc; } #btcpay-input-price { -moz-appearance: none; -webkit-appearance: none; border: none; box-shadow: none; text-align: center; font-size: 25px; margin: auto; border-radius: 5px; line-height: 35px; background: #fff; } #btcpay-input-price::-webkit-outer-spin-button, #btcpay-input-price::-webkit-inner-spin-button { -webkit-appearance: none; margin: 0; } </style>\r\n<form method=\"POST\"  action=\"https://btcpay.coincharge.io/api/v1/invoices\" class=\"btcpay-form btcpay-form--block\">\r\n  <input type=\"hidden\" name=\"storeId\" value=\"79wZ5YxFZjftBeJciuKuKAzXbstc24bn8nFDaQPXcJiQ\" />\r\n  <input type=\"hidden\" name=\"checkoutDesc\" value=\"Thank You So Much For Donating\" />\r\n  <input type=\"hidden\" name=\"notifyEmail\" value=\"alappan077@gmail.com\" />\r\n  <input type=\"hidden\" name=\"currency\" value=\"USD\" />\r\n  <input type=\"image\" class=\"submit\" name=\"submit\" src=\"https://btcpay.coincharge.io/img/paybutton/pay.svg\" style=\"width:309px; height:109px;\" alt=\"Pay with BtcPay, Self-Hosted Bitcoin Payment Processor\">\r\n</form>"},{"id":"silex-id-1633816001125-1","tagName":"DIV","type":"text-element","alt":null,"title":null,"isSectionContent":false,"visibility":{"desktop":true,"mobile":true},"style":{"mobile":{},"desktop":{"width":"312px","height":"245px","position":"absolute","top":"316.00006675720215px","left":"94.87501525878906px"}},"data":{"component":null},"children":[],"pageNames":["page-page-1"],"classList":[],"attr":{},"link":null,"enableEdit":true,"enableDrag":true,"enableDrop":false,"enableResize":{"top":true,"bottom":true,"left":true,"right":true},"selected":false,"useMinHeight":true,"innerHtml":"<h1>Please Help Donate To Keep This Site UP<br></h1>"},{"id":"silex-id-1633817675592-3","tagName":"DIV","type":"image-element","alt":null,"title":null,"isSectionContent":false,"visibility":{"desktop":true,"mobile":true},"style":{"mobile":{},"desktop":{"width":"368px","height":"268px","position":"absolute","top":"48px","left":"95px"}},"data":{"component":null},"children":[],"pageNames":["page-page-1"],"classList":[],"attr":{},"link":null,"enableEdit":true,"enableDrag":true,"enableDrop":false,"enableResize":{"top":true,"bottom":true,"left":true,"right":true},"selected":false,"useMinHeight":false,"innerHtml":"<img src=\"/ce/github/get/e/main/ngsm.gif\" />"},{"id":"silex-id-1633817725897-4","tagName":"DIV","type":"text-element","alt":null,"title":null,"isSectionContent":false,"visibility":{"desktop":true,"mobile":true},"style":{"mobile":{},"desktop":{"width":"271px","height":"95px","position":"absolute","top":"198px","left":"452px"}},"data":{"component":null},"children":[],"pageNames":["page-page-1"],"classList":[],"attr":{},"link":null,"enableEdit":true,"enableDrag":true,"enableDrop":false,"enableResize":{"top":true,"bottom":true,"left":true,"right":true},"selected":false,"useMinHeight":true,"innerHtml":"<p><ul><li>Help Make New Stuff</li><li>Help Keep This Site Up</li><li>Help Make This Site</li></ul></p>"},{"id":"silex-id-1633817803466-5","tagName":"DIV","type":"text-element","alt":null,"title":null,"isSectionContent":false,"visibility":{"desktop":true,"mobile":true},"style":{"mobile":{},"desktop":{"width":"157px","height":"154px","position":"absolute","top":"77px","left":"490px"}},"data":{"component":null},"children":[],"pageNames":["page-page-1"],"classList":[],"attr":{},"link":null,"enableEdit":true,"enableDrag":true,"enableDrop":false,"enableResize":{"top":true,"bottom":true,"left":true,"right":true},"selected":false,"useMinHeight":true,"innerHtml":"<h1>Please Donate</h1><p>to</p>"}]}